README.md
setup.py
errors/avatar_errors.py
errors/core_errors.py
errors/geometry_errors.py
errors/render_errors.py
errors/tool_errors.py
examples/pygame_integration.py
examples/snake.py
pygame_integration/__init__.py
pygame_integration/errors.py
pygame_integration/resources.py
sim32/__init__.py
sim32/avatars.py
sim32/basic_render_resources.py
sim32/core.py
sim32/geometry.py
sim32/interfaces.py
sim32/renders.py
sim32/tools.py
sim32.egg-info/PKG-INFO
sim32.egg-info/SOURCES.txt
sim32.egg-info/dependency_links.txt
sim32.egg-info/requires.txt
sim32.egg-info/top_level.txt