Metadata-Version: 2.1
Name: sim32
Version: 2.0.0
Summary: Library to help you write games
Home-page: https://github.com/TheArtur128/SimEngine
Download-URL: https://github.com/TheArtur128/SimEngine/archive/refs/tags/2.0.0.zip
Author: Arthur
Author-email: s9339307190@gmail.com
Requires-Python: >=3.10
